b2b_saas2saas/__init__.py
b2b_saas2saas/main.py
b2b_saas2saas-1.0.1.dist-info/licenses/LICENSE
b2b_saas2saas-1.0.1.dist-info/METADATA
b2b_saas2saas-1.0.1.dist-info/WHEEL
b2b_saas2saas-1.0.1.dist-info/top_level.txt
b2b_saas2saas-1.0.1.dist-info/RECORD
