Metadata-Version: 2.4
Name: b2b_saas2saas
Version: 1.0.1
Summary: A package to generate random SaaS ideas using ChatGPT
Home-page: https://github.com/25benjaminli/b2b_saas2saas
Author: Benjamin Li
Author-email: 25benjaminli@gmail.com
Classifier: Programming Language :: Python :: 3
Classifier: License :: OSI Approved :: MIT License
Classifier: Operating System :: OS Independent
Requires-Python: >=3.7
License-File: LICENSE
Requires-Dist: openai
Requires-Dist: python-dotenv
Dynamic: author
Dynamic: author-email
Dynamic: classifier
Dynamic: description
Dynamic: description-content-type
Dynamic: home-page
Dynamic: license-file
Dynamic: requires-dist
Dynamic: requires-python
Dynamic: summary
